django_library_restful/__init__.py
django_library_restful/admin.py
django_library_restful/apps.py
django_library_restful/models.py
django_library_restful/permisions.py
django_library_restful/router.py
django_library_restful/serializer.py
django_library_restful/tests.py
django_library_restful/views.py
django_library_restful/migrations/__init__.py
django_library_restful/static/__init__.py
django_library_restful/templates/__init__.py
django_library_restful-0.0.11.dist-info/LICENSE
django_library_restful-0.0.11.dist-info/METADATA
django_library_restful-0.0.11.dist-info/WHEEL
django_library_restful-0.0.11.dist-info/top_level.txt
django_library_restful-0.0.11.dist-info/RECORD
