Metadata-Version: 2.1
Name: django-library-restful
Version: 0.0.11
Summary: a django library manager
Home-page: https://github.com/MHolger77/django-libraries
Author: mohammad hosein shamsaei
Author-email: mh.shamsaei.ms@gmail.com
License: UNKNOWN
Platform: UNKNOWN
Classifier: Environment :: Web Environment
Classifier: Programming Language :: Python :: 3
Classifier: License :: OSI Approved :: MIT License
Classifier: Operating System :: OS Independent
Classifier: Framework :: Django
Classifier: Intended Audience :: Developers
Classifier: Topic :: Internet :: WWW/HTTP
